lab2/FPCVT.v
module FPCVT(
    input wire [11:0] D,
    output reg S,
    output reg [2:0] E,
    output reg [3:0] F
);

    reg [11:0] magnitude;
    integer shift_amount;
    reg [11:0] shifted;
    
    always @(*) begin
        S = D[11];
        //If D is -2048, hardcode the conversion from two's complement to floating point
        if (D == 12'b100000000000) begin
            E = 3'b111;
            F = 4'b1111;
        end


        else begin // everything else

            // If positive keep mag, if negative, take 2's complement
            if (S == 1'b0) begin
                magnitude = D;
            end else begin
                magnitude = ~D + 1;
            end

            // If magnitude is 0, set E and F to 0, otherwise just count leading zeroes
            //     (The spec only specified the E for leading zeroes, so hardcoding otherwise)
            if (magnitude == 12'b000000000000) begin
                E = 3'b000;
                F = 4'b0000;
            end else begin
                // Count leading zeroes
                E = count_leading_zeroes_set_E(magnitude);
                shift_amount = 3'd7 - E + 1; // calculate how much to shift based on what we set E. 
                shifted = magnitude << shift_amount;
                F = shifted[11:8];
            end


        end


    end


    function automatic [2:0] count_leading_zeroes_set_E(input [11:0] magnitude);
    begin
        if (magnitude[10])      count_leading_zeroes_set_E = 3'd7; // 1 leading 0
        else if (magnitude[9])  count_leading_zeroes_set_E = 3'd6;
        else if (magnitude[8])  count_leading_zeroes_set_E = 3'd5;
        else if (magnitude[7])  count_leading_zeroes_set_E = 3'd4;
        else if (magnitude[6])  count_leading_zeroes_set_E = 3'd3;
        else if (magnitude[5])  count_leading_zeroes_set_E = 3'd2;
        else if (magnitude[4])  count_leading_zeroes_set_E = 3'd1; // 7 leading 0s
        else count_leading_zeroes_set_E = 3'd0; // 8 leading 0s or more
    end
    endfunction

endmodule

lab2/FPCVT_tb.v

`timescale 1ns/1ps

module FPCVT_tb;

    reg [11:0] D;
    wire S;
    wire [2:0] E;
    wire [3:0] F;

    FPCVT uut (
        .D(D),
        .S(S),
        .E(E),
        .F(F)
    );

    initial begin
        $monitor("Time=%0t | D=%b | S=%b | E=%b | F=%b", $time, D, S, E, F);
        $dumpfile("wave.vcd");
        $dumpvars(0, FPCVT_tb);
        // Test zero
        D = 12'b000000000000;
        #10;

        // Test maximum positive value
        D = 12'b011111111111; // 2047
        #10;

        // Test minimum negative value (-2048)
        D = 12'b100000000000;
        #10;

        // Test -2047
        D = 12'b100000000001;
        #10;

        // Test -1
        D = 12'b111111111111;
        #10;

        // small positive numbers
        D = 12'b000000000001;  // +1
        #10;
        D = 12'b000000000010;  // +2
        #10;
        D = 12'b000000010000;  // +16
        #10;

        // small negative numbers
        D = 12'b111111111111;  // -1
        #10;
        D = 12'b111111111110;  // -2
        #10;
        D = 12'b111111100000;  // -16
        #10;

        // positives
        D = 12'b000010101101;  // e.g., +173 decimal
        #10;


        $finish;
    end

endmodule

lab2/wave.vcd
$date
	Sun Apr 27 15:20:38 2025
$end
$version
	Icarus Verilog
$end
$timescale
	1ps
$end
$scope module FPCVT_tb $end
$var wire 1 ! S $end
$var wire 4 " F [3:0] $end
$var wire 3 # E [2:0] $end
$var reg 12 $ D [11:0] $end
$scope module uut $end
$var wire 12 % D [11:0] $end
$var reg 3 & E [2:0] $end
$var reg 4 ' F [3:0] $end
$var reg 1 ! S $end
$var reg 12 ( magnitude [11:0] $end
$var reg 12 ) shifted [11:0] $end
$var integer 32 * shift_amount [31:0] $end
$scope function count_leading_zeroes_set_E $end
$upscope $end
$upscope $end
$upscope $end
$enddefinitions $end
$comment Show the parameter values. $end
$dumpall
$end
#0
$dumpvars
bx *
bx )
b0 (
b0 '
b0 &
b0 %
b0 $
b0 #
b0 "
0!
$end
#10000
b1111 "
b1111 '
b111111111110 )
b1 *
b111 #
b111 &
b11111111111 (
b11111111111 $
b11111111111 %
#20000
1!
b100000000000 $
b100000000000 %
#30000
b100000000001 $
b100000000001 %
#40000
b1 "
b1 '
b100000000 )
b1000 *
b0 #
b0 &
b1 (
b111111111111 $
b111111111111 %
#50000
0!
b1 $
b1 %
#60000
b10 "
b10 '
b1000000000 )
b10 (
b10 $
b10 %
#70000
b1000 "
b1000 '
b100000000000 )
b111 *
b1 #
b1 &
b10000 (
b10000 $
b10000 %
#80000
b1 "
b1 '
b100000000 )
b1000 *
b0 #
b0 &
b1 (
1!
b111111111111 $
b111111111111 %
#90000
b10 "
b10 '
b1000000000 )
b10 (
b111111111110 $
b111111111110 %
#100000
b1000 "
b1000 '
b100000000000 )
b110 *
b10 #
b10 &
b100000 (
b111111100000 $
b111111100000 %
#110000
b1010 "
b1010 '
b101011010000 )
b100 *
b100 #
b100 &
b10101101 (
0!
b10101101 $
b10101101 %
